rai_toolbox/__init__.py
rai_toolbox/_typing.py
rai_toolbox/_version.py
rai_toolbox/py.typed
rai_toolbox/_utils/__init__.py
rai_toolbox/_utils/itertools.py
rai_toolbox/_utils/stateful.py
rai_toolbox/_utils/tqdm.py
rai_toolbox/augmentations/__init__.py
rai_toolbox/augmentations/augmix/__init__.py
rai_toolbox/augmentations/augmix/_implementation.py
rai_toolbox/augmentations/augmix/transforms.py
rai_toolbox/augmentations/fourier/__init__.py
rai_toolbox/augmentations/fourier/_fourier_basis.py
rai_toolbox/augmentations/fourier/_implementations.py
rai_toolbox/augmentations/fourier/transforms.py
rai_toolbox/datasets/__init__.py
rai_toolbox/datasets/_cifar10_base.py
rai_toolbox/datasets/_imagenet_base.py
rai_toolbox/datasets/_utils.py
rai_toolbox/datasets/cifar10_extensions.py
rai_toolbox/datasets/cifar_corruptions.py
rai_toolbox/losses/__init__.py
rai_toolbox/losses/_jensen_shannon_divergence.py
rai_toolbox/losses/_utils.py
rai_toolbox/mushin/__init__.py
rai_toolbox/mushin/_compatibility.py
rai_toolbox/mushin/_utils.py
rai_toolbox/mushin/hydra.py
rai_toolbox/mushin/workflows.py
rai_toolbox/mushin/lightning/__init__.py
rai_toolbox/mushin/lightning/_pl_main.py
rai_toolbox/mushin/lightning/callbacks.py
rai_toolbox/mushin/lightning/launchers.py
rai_toolbox/mushin/testing/__init__.py
rai_toolbox/mushin/testing/lightning.py
rai_toolbox/optim/__init__.py
rai_toolbox/optim/frank_wolfe.py
rai_toolbox/optim/lp_space.py
rai_toolbox/optim/misc.py
rai_toolbox/optim/optimizer.py
rai_toolbox/perturbations/__init__.py
rai_toolbox/perturbations/init.py
rai_toolbox/perturbations/models.py
rai_toolbox/perturbations/solvers.py
rai_toolbox-0.2.1.dist-info/LICENSE.txt
rai_toolbox-0.2.1.dist-info/METADATA
rai_toolbox-0.2.1.dist-info/WHEEL
rai_toolbox-0.2.1.dist-info/top_level.txt
rai_toolbox-0.2.1.dist-info/RECORD
