Metadata-Version: 2.1
Name: rai-toolbox
Version: 0.2.1
Summary: PyTorch-centric library for evaluating and enhancing the robustness of AI technologies
Home-page: https://github.com/mit-ll-responsible-ai/responsible-ai-toolbox
Author: Ryan Soklaski, Justin Goodwin, Olivia Brown, Michael Yee
Author-email: ryan.soklaski@ll.mit.edu
License: MIT
Download-URL: https://github.com/mit-ll-responsible-ai/responsible-ai-toolbox/tarball/v0.2.1
Keywords: machine learning robustness pytorch responsible AI
Platform: UNKNOWN
Classifier: Development Status :: 4 - Beta
Classifier: License :: OSI Approved :: MIT License
Classifier: Operating System :: OS Independent
Classifier: Intended Audience :: Science/Research
Classifier: Programming Language :: Python :: 3.7
Classifier: Programming Language :: Python :: 3.8
Classifier: Programming Language :: Python :: 3.9
Classifier: Topic :: Scientific/Engineering
Requires-Python: >=3.7
License-File: LICENSE.txt
Requires-Dist: torchvision (>=0.10.0)
Requires-Dist: torch (!=1.9.1,>=1.9.0)
Requires-Dist: torchmetrics (>=0.6.0)
Requires-Dist: typing-extensions (>=4.1.1)
Provides-Extra: mushin
Requires-Dist: pytorch-lightning (>=1.5.0) ; extra == 'mushin'
Requires-Dist: hydra-zen (>=0.7.0) ; extra == 'mushin'
Requires-Dist: xarray (>=0.19.0) ; extra == 'mushin'
Requires-Dist: matplotlib (>=3.3) ; extra == 'mushin'
Requires-Dist: protobuf (<=3.20.1) ; extra == 'mushin'
Provides-Extra: tests
Requires-Dist: pytest (>=3.8) ; extra == 'tests'
Requires-Dist: hypothesis (>=6.41.0) ; extra == 'tests'
Requires-Dist: mygrad (>=2.0.0) ; extra == 'tests'
Requires-Dist: omegaconf (>=2.1.1) ; extra == 'tests'
Requires-Dist: netCDF4 (>=1.5.8) ; extra == 'tests'
